comfy_ui_mcp_server/__init__.py
comfy_ui_mcp_server/server.py
mseep_comfy_ui_mcp_server-0.1.1.dist-info/METADATA
mseep_comfy_ui_mcp_server-0.1.1.dist-info/WHEEL
mseep_comfy_ui_mcp_server-0.1.1.dist-info/entry_points.txt
mseep_comfy_ui_mcp_server-0.1.1.dist-info/licenses/LICENSE
mseep_comfy_ui_mcp_server-0.1.1.dist-info/RECORD
